lib3970/__init__.py
lib3970/targeting.py
lib3970/util.py
lib3970/ik/__init__.py
lib3970/ik/ik_3970.py
lib3970/ik/turret_ik_example.py
lib3970/limelight/__init__.py
lib3970/limelight/camera.py
lib3970/limelight/dataclasses.py
lib3970/limelight/manager.py
lib3970/math/__init__.py
lib3970/math/interpolation.py
lib3970-0.3.7.dist-info/licenses/LICENSE
lib3970-0.3.7.dist-info/METADATA
lib3970-0.3.7.dist-info/WHEEL
lib3970-0.3.7.dist-info/top_level.txt
lib3970-0.3.7.dist-info/RECORD
