Metadata-Version: 2.4
Name: lib3970
Version: 0.3.7
Summary: A handful of utility functions and classes used by FRC team 3970
Author-email: Joel Velez <jvelez3970@gmail.com>
License: MIT
Requires-Python: >=3.10
License-File: LICENSE
Requires-Dist: robotpy-native-ntcore>=2026.1.1
Requires-Dist: numpy>=2.3.5
Requires-Dist: phoenix6>=26.1.0
Requires-Dist: wpilib>=2026.2.1
Dynamic: license-file
